{
 "accept_payment": 0,
 "allow_comments": 0,
 "allow_delete": 0,
 "allow_edit": 0,
 "allow_incomplete": 1,
 "allow_multiple": 0,
 "allow_print": 0,
 "amount": 0.0,
 "amount_based_on_field": 0,
 "apply_document_permissions": 0,
 "button_label": "Save",
 "creation": "2022-12-21 15:16:26.041624",
 "currency": "INR",
 "doc_type": "Followup Form",
 "docstatus": 0,
 "doctype": "Web Form",
 "idx": 0,
 "is_standard": 1,
 "list_columns": [],
 "login_required": 0,
 "max_attachment_size": 0,
 "modified": "2022-12-21 15:28:18.613017",
 "modified_by": "Administrator",
 "module": "Construction",
 "name": "followup-form",
 "owner": "Administrator",
 "payment_button_label": "Buy Now",
 "published": 1,
 "route": "followup-form",
 "show_attachments": 0,
 "show_list": 0,
 "show_sidebar": 0,
 "title": "Followup Form",
 "web_form_fields": [
  {
   "allow_read_on_all_link_options": 0,
   "fieldname": "project",
   "fieldtype": "Link",
   "hidden": 0,
   "label": "Project",
   "max_length": 0,
   "max_value": 0,
   "options": "Project",
   "read_only": 0,
   "reqd": 1,
   "show_in_filter": 0
  },
  {
   "allow_read_on_all_link_options": 0,
   "fieldname": "posting_date",
   "fieldtype": "Date",
   "hidden": 0,
   "label": "Posting Date",
   "max_length": 0,
   "max_value": 0,
   "read_only": 0,
   "reqd": 1,
   "show_in_filter": 0
  },
  {
   "allow_read_on_all_link_options": 0,
   "fieldname": "project_doctypes_list",
   "fieldtype": "Table",
   "hidden": 0,
   "label": "Project Doctypes List",
   "max_length": 0,
   "max_value": 0,
   "options": "Project Doctypes List",
   "read_only": 0,
   "reqd": 0,
   "show_in_filter": 0
  },
  {
   "allow_read_on_all_link_options": 0,
   "fieldname": "amended_from",
   "fieldtype": "Link",
   "hidden": 0,
   "label": "Amended From",
   "max_length": 0,
   "max_value": 0,
   "options": "Followup Form",
   "read_only": 1,
   "reqd": 0,
   "show_in_filter": 0
  },
  {
   "allow_read_on_all_link_options": 0,
   "fieldname": "project",
   "fieldtype": "Link",
   "hidden": 0,
   "label": "Project",
   "max_length": 0,
   "max_value": 0,
   "options": "Project",
   "read_only": 0,
   "reqd": 1,
   "show_in_filter": 0
  },
  {
   "allow_read_on_all_link_options": 0,
   "fieldname": "posting_date",
   "fieldtype": "Date",
   "hidden": 0,
   "label": "Posting Date",
   "max_length": 0,
   "max_value": 0,
   "read_only": 0,
   "reqd": 1,
   "show_in_filter": 0
  },
  {
   "allow_read_on_all_link_options": 0,
   "fieldname": "project_doctypes_list",
   "fieldtype": "Table",
   "hidden": 0,
   "label": "Project Doctypes List",
   "max_length": 0,
   "max_value": 0,
   "options": "Project Doctypes List",
   "read_only": 0,
   "reqd": 0,
   "show_in_filter": 0
  },
  {
   "allow_read_on_all_link_options": 0,
   "fieldname": "amended_from",
   "fieldtype": "Link",
   "hidden": 0,
   "label": "Amended From",
   "max_length": 0,
   "max_value": 0,
   "options": "Followup Form",
   "read_only": 1,
   "reqd": 0,
   "show_in_filter": 0
  },
  {
   "allow_read_on_all_link_options": 0,
   "fieldname": "route",
   "fieldtype": "Data",
   "hidden": 0,
   "label": "route",
   "max_length": 0,
   "max_value": 0,
   "read_only": 0,
   "reqd": 0,
   "show_in_filter": 0
  },
  {
   "allow_read_on_all_link_options": 0,
   "default": "1",
   "fieldname": "is_published",
   "fieldtype": "Check",
   "hidden": 0,
   "label": "is published",
   "max_length": 0,
   "max_value": 0,
   "read_only": 0,
   "reqd": 0,
   "show_in_filter": 0
  },
  {
   "allow_read_on_all_link_options": 0,
   "fieldname": "project",
   "fieldtype": "Link",
   "hidden": 0,
   "label": "Project",
   "max_length": 0,
   "max_value": 0,
   "options": "Project",
   "read_only": 0,
   "reqd": 1,
   "show_in_filter": 0
  },
  {
   "allow_read_on_all_link_options": 0,
   "fieldname": "posting_date",
   "fieldtype": "Date",
   "hidden": 0,
   "label": "Posting Date",
   "max_length": 0,
   "max_value": 0,
   "read_only": 0,
   "reqd": 1,
   "show_in_filter": 0
  },
  {
   "allow_read_on_all_link_options": 0,
   "fieldname": "project_doctypes_list",
   "fieldtype": "Table",
   "hidden": 0,
   "label": "Project Doctypes List",
   "max_length": 0,
   "max_value": 0,
   "options": "Project Doctypes List",
   "read_only": 0,
   "reqd": 0,
   "show_in_filter": 0
  },
  {
   "allow_read_on_all_link_options": 0,
   "fieldname": "amended_from",
   "fieldtype": "Link",
   "hidden": 0,
   "label": "Amended From",
   "max_length": 0,
   "max_value": 0,
   "options": "Followup Form",
   "read_only": 1,
   "reqd": 0,
   "show_in_filter": 0
  },
  {
   "allow_read_on_all_link_options": 0,
   "fieldname": "route",
   "fieldtype": "Data",
   "hidden": 0,
   "label": "route",
   "max_length": 0,
   "max_value": 0,
   "read_only": 0,
   "reqd": 0,
   "show_in_filter": 0
  },
  {
   "allow_read_on_all_link_options": 0,
   "default": "1",
   "fieldname": "is_published",
   "fieldtype": "Check",
   "hidden": 0,
   "label": "is published",
   "max_length": 0,
   "max_value": 0,
   "read_only": 0,
   "reqd": 0,
   "show_in_filter": 0
  }
 ]
}